CHANGES.txt
LICENSE-2.0.txt
MANIFEST.in
README.rst
requirements.txt
setup.cfg
setup.py
release_manager/__init__.py
release_manager/__main__.py
release_manager/_version.py
release_manager/logger.py
release_manager/package.py
release_manager/utils.py
release_manager.egg-info/PKG-INFO
release_manager.egg-info/SOURCES.txt
release_manager.egg-info/dependency_links.txt
release_manager.egg-info/entry_points.txt
release_manager.egg-info/requires.txt
release_manager.egg-info/top_level.txt
release_manager/targets/__init__.py
release_manager/targets/bintray.py
release_manager/test/__init__.py