Metadata-Version: 1.1
Name: release-manager
Version: 0.1.0-rc3
Summary: Utility for creating and uploading zip packages
Home-page: https://github.com/snowplow/release-manager
Author: Joshua Beemster
Author-email: support@snowplowanalytics.com
License: http://www.apache.org/licenses/LICENSE-2.0
Download-URL: https://github.com/snowplow/release-manager/tarball/0.1.0
Platform: UNKNOWN
